quantbox/__init__.py
quantbox/quantbox.py
quantbox/witapi.py
witapi/__init__.py
witapi/quantbox.py
quantbox-0.0.13.dist-info/METADATA
quantbox-0.0.13.dist-info/WHEEL
quantbox-0.0.13.dist-info/top_level.txt
quantbox-0.0.13.dist-info/RECORD
