Metadata-Version: 2.1
Name: quantbox
Version: 0.0.13
Summary: quantbox wit api
Home-page: UNKNOWN
Author: ffolio
Author-email: service@ffolio.co.kr
License: UNKNOWN
Keywords: pypi deploy
Platform: UNKNOWN
Classifier: Programming Language :: Python :: 3
Classifier: Programming Language :: Python :: 3.2
Classifier: Programming Language :: Python :: 3.3
Classifier: Programming Language :: Python :: 3.4
Classifier: Programming Language :: Python :: 3.5
Classifier: Programming Language :: Python :: 3.6
Classifier: Programming Language :: Python :: 3.7
Requires-Python: >=3
Requires-Dist: motoo (>=1.1.89)
Requires-Dist: orjson (>=3.7.7)
Requires-Dist: requests (==2.26.0)
